apytl/__init__.py
apytl/bar.py
apytl-0.0a7.dist-info/LICENSE
apytl-0.0a7.dist-info/METADATA
apytl-0.0a7.dist-info/WHEEL
apytl-0.0a7.dist-info/top_level.txt
apytl-0.0a7.dist-info/RECORD
