Metadata-Version: 2.1
Name: apytl
Version: 0.0a7
Summary: A bawdy, emoji-friendly progress bar.
Home-page: https://github.com/anadolski/apytl
Author: Andrew Nadolski
Author-email: andrew.nadolski@gmail.com
License: UNKNOWN
Platform: Linux
Platform: MacOS X
Classifier: Programming Language :: Python :: 3
Classifier: License :: OSI Approved :: BSD License
Classifier: Operating System :: MacOS :: MacOS X
Classifier: Operating System :: POSIX :: Linux
Classifier: Development Status :: 3 - Alpha
Requires-Python: >=3.5
